qrc/__init__.py
qrc/__main__.py
qrc_tool-1.0.1.dist-info/licenses/LICENSE
qrc_tool-1.0.1.dist-info/METADATA
qrc_tool-1.0.1.dist-info/WHEEL
qrc_tool-1.0.1.dist-info/entry_points.txt
qrc_tool-1.0.1.dist-info/top_level.txt
qrc_tool-1.0.1.dist-info/RECORD
