Metadata-Version: 2.4
Name: qrc-tool
Version: 1.0.1
Summary: A simple command-line QR code generator
Author-email: Denis Pirogov <epluribusneo@ya.ru>
License: MIT
Project-URL: Homepage, https://epluribusneo.ru
Project-URL: Repository, https://github.com/EpluribusNEO/qrc
Project-URL: Issues, https://github.com/EpluribusNEO/qrc/issues
Keywords: qr,qrcode,cli,generator,text,tool
Classifier: Development Status :: 5 - Production/Stable
Classifier: Environment :: Console
Classifier: Intended Audience :: End Users/Desktop
Classifier: License :: OSI Approved :: MIT License
Classifier: Operating System :: OS Independent
Classifier: Programming Language :: Python :: 3
Classifier: Programming Language :: Python :: 3.8
Classifier: Programming Language :: Python :: 3.9
Classifier: Programming Language :: Python :: 3.10
Classifier: Programming Language :: Python :: 3.11
Classifier: Programming Language :: Python :: 3.12
Classifier: Programming Language :: Python :: 3.13
Classifier: Topic :: Utilities
Requires-Python: >=3.8
License-File: LICENSE
Requires-Dist: qrcode[pil]>=7.0
Dynamic: license-file
